react_i18next_lint/__init__.py
react_i18next_lint/commands/__init__.py
react_i18next_lint/commands/extract_keys.py
react_i18next_lint/commands/group_key_locales.py
react_i18next_lint/commands/validate_keys.py
react_i18next_lint/main.py
react_i18next_lint-0.1.0.dist-info/LICENSE
react_i18next_lint-0.1.0.dist-info/METADATA
react_i18next_lint-0.1.0.dist-info/WHEEL
react_i18next_lint-0.1.0.dist-info/entry_points.txt
react_i18next_lint-0.1.0.dist-info/RECORD
