Metadata-Version: 2.1
Name: react-i18next-lint
Version: 0.1.0
Summary: A small lint tool for react-i18next phrases and usage
Home-page: https://github.com/jimexist/react-i18next-lint
License: MIT
Keywords: react,i18next,lint,i18n
Author: Jiayu Liu
Author-email: jiayu@hey.com
Requires-Python: >=3.10,<4.0
Classifier: License :: OSI Approved :: MIT License
Classifier: Programming Language :: Python :: 3
Classifier: Programming Language :: Python :: 3.10
Classifier: Programming Language :: Python :: 3.11
Classifier: Topic :: Software Development :: Build Tools
Requires-Dist: duckdb (>=0.10.3,<0.11.0)
Requires-Dist: rich (>=13.7.1,<14.0.0)
Requires-Dist: typer (>=0.12.3,<0.13.0)
Project-URL: Repository, https://github.com/jimexist/react-i18next-lint
